databricks_dspy/__init__.py
databricks_dspy/clients/__init__.py
databricks_dspy/clients/databricks_lm.py
databricks_dspy/retrievers/__init__.py
databricks_dspy/retrievers/databricks_rm.py
databricks_dspy-0.1.0.dist-info/METADATA
databricks_dspy-0.1.0.dist-info/WHEEL
databricks_dspy-0.1.0.dist-info/RECORD
