Metadata-Version: 2.4
Name: databricks-dspy
Version: 0.1.0
Summary: Databricks integration for DSPy
Author-email: Databricks <agent-feedback@databricks.com>
License: Apache-2.0
Requires-Python: >=3.10
Requires-Dist: databricks-sdk>=0.58.0
Requires-Dist: dspy>=2.6.27
Requires-Dist: mlflow>=3.0.0
Provides-Extra: dev
Requires-Dist: pytest; extra == 'dev'
Requires-Dist: ruff; extra == 'dev'
